Metadata-Version: 1.2
Name: kdGUI
Version: 1.0.0
Summary: UNKNOWN
Home-page: https://github.com/bkdwei/kdGUI
Author: bkdwei
Author-email: bkdwei@163.com
Maintainer: 韦坤东
Maintainer-email: bkdwei@163.com
License: MIT
Keywords: tkinter,gui
Platform: any
Classifier:  Development Status :: 2 - Pre-Alpha
Classifier: Environment :: X11 Applications :: Qt
Classifier: Intended Audience :: Developers
Classifier: Natural Language :: Chinese (Simplified)
Classifier: Topic :: Software Development :: User Interfaces
Classifier: Programming Language :: Python :: 3
Classifier:  License :: OSI Approved :: MIT License
Classifier: Operating System :: POSIX
Classifier: Operating System :: Microsoft :: Windows
